<?xml version="1.0" encoding="utf-8"?><RoboViewModel xmlns:xsd="http://www.w3.org/2001/XMLSchema" xmlns:xsi="http://www.w3.org/2001/XMLSchema-instance"><TestSuitCollection><TestSuitViewModel><Description>New suit desc3</Description><IsExpanded>true</IsExpanded><IsSelected>false</IsSelected><Name>New Suit 1AlteredAltered</Name><AllCollection><anyType xsi:type="TestSequenceViewModel"><Description>3rd Sequence desc</Description><IconPath>/Icons/sequence.png</IconPath><IsExpanded>true</IsExpanded><IsSelected>false</IsSelected><TestStepCollection><TestStepViewModel><Description>3rd Sequence desc</Description><IsExpanded>true</IsExpanded><IsSelected>false</IsSelected><Name>Nth Step</Name></TestStepViewModel><TestStepViewModel><Description>3rd Sequence desc</Description><IsExpanded>true</IsExpanded><IsSelected>false</IsSelected><Name>Nth Step2</Name></TestStepViewModel></TestStepCollection><Name>3rd Sequence</Name></anyType><anyType xsi:type="DataSourceViewModel"><Name>3rd Data Source</Name><Description>3rd DS desc</Description><SelectedIndex>0</SelectedIndex><SourceTypes><DataSource><Name>Database</Name></DataSource><DataSource><Name>Excel Sheet</Name></DataSource><DataSource><Name>CSV File</Name></DataSource></SourceTypes><SelectedDataSource xsi:type="DataBase"><SelectedDataBaseTypeIndex>0</SelectedDataBaseTypeIndex><SelectedDataBaseType>Oracle</SelectedDataBaseType><DatabaseTypes><string>MS SQL Server</string><string>Oracle</string><string>MySQL</string></DatabaseTypes><DatabaseHost>aaa</DatabaseHost><DatabasePort>sss</DatabasePort><UserName>ddd</UserName><Password>fff</Password><Query>qqqqqqqqq</Query></SelectedDataSource><IconPath>/Icons/data_source.png</IconPath><IsSelected>false</IsSelected></anyType><anyType xsi:type="TestSequenceViewModel"><Description>3rd Sequence desc1</Description><IconPath>/Icons/sequence.png</IconPath><IsExpanded>false</IsExpanded><IsSelected>false</IsSelected><TestStepCollection /><Name>3rd Sequence</Name></anyType></AllCollection></TestSuitViewModel><TestSuitViewModel><Description>New suit desc</Description><IsExpanded>true</IsExpanded><IsSelected>false</IsSelected><Name>New Suit 2</Name><AllCollection><anyType xsi:type="TestSequenceViewModel"><Description>3rd Sequence desc</Description><IconPath>/Icons/sequence.png</IconPath><IsExpanded>true</IsExpanded><IsSelected>false</IsSelected><TestStepCollection><TestStepViewModel><Description>3rd Step desc</Description><IsExpanded>true</IsExpanded><IsSelected>false</IsSelected><Name>Nth Step</Name></TestStepViewModel></TestStepCollection><Name>3rd Sequence</Name></anyType><anyType xsi:type="DataSourceViewModel"><Name>3rd Data Source</Name><Description>3rd DS desc</Description><SelectedIndex>1</SelectedIndex><SourceTypes><DataSource><Name>Database</Name></DataSource><DataSource><Name>Excel Sheet</Name></DataSource><DataSource><Name>CSV File</Name></DataSource></SourceTypes><SelectedDataSource xsi:type="ExcelSheet"><ExcelSheetPath>C:\Users\bipadh\Downloads\Automation results_11_Sep_2016.xlsx</ExcelSheetPath><SorkSheets /><FirstRowContainsHeader>true</FirstRowContainsHeader></SelectedDataSource><IconPath>/Icons/data_source.png</IconPath><IsSelected>false</IsSelected></anyType><anyType xsi:type="VariableViewModel"><Name>3rd Variable1</Name><Key>kkk</Key><SelectedVarTypeIndex>1</SelectedVarTypeIndex><VarType>Random Number</VarType><MinValue>0</MinValue><MaxValue>0</MaxValue><Description>3rd Variable desc</Description><IconPath>/Icons/variable.png</IconPath><IsExpanded>true</IsExpanded><IsSelected>false</IsSelected></anyType><anyType xsi:type="AppsViewModel"><_AppTypes><string>Chrome</string><string>Firefox</string><string>IE</string><string>EDGE</string><string>Safari</string><string>Outlook</string><string>Other</string></_AppTypes><Name>3rd Apps</Name><Description>3rd App desc</Description><SelectedIndex>4</SelectedIndex><AppTypes><string>Chrome</string><string>Firefox</string><string>IE</string><string>EDGE</string><string>Safari</string><string>Outlook</string><string>Other</string></AppTypes><AppPath>C:\Program Files (x86)\Safari\Safari.exe</AppPath><IconPath>/Icons/app.png</IconPath><IsExpanded>true</IsExpanded><IsSelected>true</IsSelected></anyType><anyType xsi:type="AppsViewModel"><_AppTypes><string>Chrome</string><string>Firefox</string><string>IE</string><string>EDGE</string><string>Safari</string><string>Outlook</string><string>Other</string></_AppTypes><Name>3rd App2</Name><Description>3rd App desc</Description><SelectedIndex>0</SelectedIndex><AppTypes><string>Chrome</string><string>Firefox</string><string>IE</string><string>EDGE</string><string>Safari</string><string>Outlook</string><string>Other</string></AppTypes><AppPath>C:\Program Files (x86)\Google\Chrome\Application\chrome.exe</AppPath><IconPath>/Icons/app.png</IconPath><IsExpanded>false</IsExpanded><IsSelected>false</IsSelected></anyType><anyType xsi:type="VariableViewModel"><Name>4th var</Name><Key>myvarkhsdf8768768</Key><SelectedVarTypeIndex>4</SelectedVarTypeIndex><VarType>Python Script</VarType><MinValue>0</MinValue><MaxValue>0</MaxValue><PythonScript>xdzsdfzsdf</PythonScript><AllowedChars>dsfsdfsd</AllowedChars><Description>4th var</Description><IconPath>/Icons/variable.png</IconPath><IsExpanded>true</IsExpanded><IsSelected>false</IsSelected></anyType></AllCollection></TestSuitViewModel></TestSuitCollection><SelectedNode xsi:type="AppsViewModel"><_AppTypes><string>Chrome</string><string>Firefox</string><string>IE</string><string>EDGE</string><string>Safari</string><string>Outlook</string><string>Other</string></_AppTypes><Name>3rd Apps</Name><Description>3rd App desc</Description><SelectedIndex>4</SelectedIndex><AppTypes><string>Chrome</string><string>Firefox</string><string>IE</string><string>EDGE</string><string>Safari</string><string>Outlook</string><string>Other</string></AppTypes><AppPath>C:\Program Files (x86)\Safari\Safari.exe</AppPath><IconPath>/Icons/app.png</IconPath><IsExpanded>true</IsExpanded><IsSelected>true</IsSelected></SelectedNode></RoboViewModel>